{
    "logo": {
        "url": "/images/logo-dark.svg",
        "altText": "Logo dark",
        "styles": {
            "self": {
                "margin": [
                    "mr-3"
                ]
            }
        },
        "type": "ImageBlock"
    },
    "primaryLinks": [
        {
            "label": "Work",
            "url": "/work",
            "icon": "arrowRight",
            "iconPosition": "right",
            "style": "secondary",
            "type": "Link",
            "altText": "work"
        },
        {
            "label": "About",
            "altText": "about",
            "url": "/about",
            "icon": "chevronDown",
            "iconPosition": "right",
            "style": "secondary",
            "type": "Link",
            "showIcon": true
        },
        {
            "label": "Careers",
            "altText": "Careers page",
            "url": "/careers",
            "icon": "arrowRight",
            "iconPosition": "right",
            "style": "secondary",
            "type": "Link"
        },
        {
            "type": "SubNav",
            "label": "Contact",
            "altText": "Dropdown",
            "links": [],
            "labelStyle": "secondary"
        }
    ],
    "secondaryLinks": [
        {
            "label": "Schedule a Call",
            "url": "/Schedule",
            "icon": "arrowRight",
            "iconPosition": "right",
            "style": "primary",
            "type": "Button",
            "altText": "Schedule a Call"
        }
    ],
    "variant": "logo-left-primary-nav-centered",
    "colors": "bg-light-fg-dark",
    "type": "Header"
}